[
  {
    "situation": "Состояние cold",
    "dialogue": "Да-да, интересно. Расскажите.",
    "emotion": "cold",
    "source": "extracted"
  },
  {
    "situation": "Состояние cold",
    "dialogue": "Ага, понимаю. Хорошо.",
    "emotion": "cold",
    "source": "extracted"
  },
  {
    "situation": "Состояние cold",
    "dialogue": "Да, я подумаю. Обязательно.",
    "emotion": "cold",
    "source": "extracted"
  },
  {
    "situation": "Состояние cold",
    "dialogue": "Звучит неплохо.",
    "emotion": "cold",
    "source": "extracted"
  },
  {
    "situation": "Состояние cold",
    "dialogue": "Ну да, наверное, надо бы разобраться.",
    "emotion": "cold",
    "source": "extracted"
  },
  {
    "situation": "Состояние guarded",
    "dialogue": "Да, я помню, вы звонили. Просто не успел ещё.",
    "emotion": "guarded",
    "source": "extracted"
  },
  {
    "situation": "Состояние guarded",
    "dialogue": "Ага, надо бы... На следующей неделе точно.",
    "emotion": "guarded",
    "source": "extracted"
  },
  {
    "situation": "Состояние guarded",
    "dialogue": "Хорошая идея. Я подумаю.",
    "emotion": "guarded",
    "source": "extracted"
  },
  {
    "situation": "Состояние guarded",
    "dialogue": "Да-да, вы правы. Я займусь.",
    "emotion": "guarded",
    "source": "extracted"
  },
  {
    "situation": "Состояние guarded",
    "dialogue": "Конечно. Обязательно. Скоро.",
    "emotion": "guarded",
    "source": "extracted"
  },
  {
    "situation": "Состояние curious",
    "dialogue": "А подождите, правда? И долг весь спишут?",
    "emotion": "curious",
    "source": "extracted"
  },
  {
    "situation": "Состояние curious",
    "dialogue": "Хм, а жене рассказать можно?",
    "emotion": "curious",
    "source": "extracted"
  },
  {
    "situation": "Состояние curious",
    "dialogue": "А это быстро? Мне бы побыстрее.",
    "emotion": "curious",
    "source": "extracted"
  },
  {
    "situation": "Состояние curious",
    "dialogue": "Интересно. Нет, правда интересно.",
    "emotion": "curious",
    "source": "extracted"
  },
  {
    "situation": "Состояние curious",
    "dialogue": "А приставы тогда отстанут?",
    "emotion": "curious",
    "source": "extracted"
  },
  {
    "situation": "Состояние considering",
    "dialogue": "Знаете, жена уже устала. Каждый день нервы.",
    "emotion": "considering",
    "source": "extracted"
  },
  {
    "situation": "Состояние considering",
    "dialogue": "Дети в школе, деньги нужны... А у меня долги.",
    "emotion": "considering",
    "source": "extracted"
  },
  {
    "situation": "Состояние considering",
    "dialogue": "Я всё откладываю-откладываю... Сам знаю.",
    "emotion": "considering",
    "source": "extracted"
  },
  {
    "situation": "Состояние considering",
    "dialogue": "Может, пора уже что-то сделать. Реально.",
    "emotion": "considering",
    "source": "extracted"
  },
  {
    "situation": "Состояние considering",
    "dialogue": "Сколько стоит? Прямо скажите.",
    "emotion": "considering",
    "source": "extracted"
  },
  {
    "situation": "Состояние negotiating",
    "dialogue": "Ладно. Что мне нужно сделать КОНКРЕТНО?",
    "emotion": "negotiating",
    "source": "extracted"
  },
  {
    "situation": "Состояние negotiating",
    "dialogue": "Паспорт сфотографировать? Прямо сейчас?",
    "emotion": "negotiating",
    "source": "extracted"
  },
  {
    "situation": "Состояние negotiating",
    "dialogue": "А оплатить когда? Число скажите.",
    "emotion": "negotiating",
    "source": "extracted"
  },
  {
    "situation": "Состояние negotiating",
    "dialogue": "Хорошо. Но напомните мне. Я забуду.",
    "emotion": "negotiating",
    "source": "extracted"
  },
  {
    "situation": "Состояние negotiating",
    "dialogue": "Давайте зафиксируем. Что и когда.",
    "emotion": "negotiating",
    "source": "extracted"
  },
  {
    "situation": "Состояние deal",
    "dialogue": "Ладно, давайте. Хватит откладывать.",
    "emotion": "deal",
    "source": "extracted"
  },
  {
    "situation": "Состояние deal",
    "dialogue": "Спасибо, что дожали. Сам бы не решился.",
    "emotion": "deal",
    "source": "extracted"
  },
  {
    "situation": "Состояние deal",
    "dialogue": "Фото паспорта отправляю. Сейчас.",
    "emotion": "deal",
    "source": "extracted"
  },
  {
    "situation": "Состояние deal",
    "dialogue": "Хорошо. Записал. Сделаю.",
    "emotion": "deal",
    "source": "extracted"
  },
  {
    "situation": "Состояние deal",
    "dialogue": "Наконец-то. Давно надо было.",
    "emotion": "deal",
    "source": "extracted"
  },
  {
    "situation": "Состояние testing",
    "dialogue": "А может, подождём ещё? Вдруг само...",
    "emotion": "testing",
    "source": "extracted"
  },
  {
    "situation": "Состояние testing",
    "dialogue": "Жена говорит — не торопись...",
    "emotion": "testing",
    "source": "extracted"
  },
  {
    "situation": "Состояние testing",
    "dialogue": "Я подумал... может, позже?",
    "emotion": "testing",
    "source": "extracted"
  },
  {
    "situation": "Состояние testing",
    "dialogue": "А если передумаю — можно?",
    "emotion": "testing",
    "source": "extracted"
  },
  {
    "situation": "Состояние testing",
    "dialogue": "Ну... не уверен... давайте на следующей неделе?",
    "emotion": "testing",
    "source": "extracted"
  },
  {
    "situation": "Состояние callback",
    "dialogue": "Да-да, перезвоните. На следующей неделе.",
    "emotion": "callback",
    "source": "extracted"
  },
  {
    "situation": "Состояние callback",
    "dialogue": "Я подумаю. Точно-точно.",
    "emotion": "callback",
    "source": "extracted"
  },
  {
    "situation": "Состояние callback",
    "dialogue": "Не, ну надо бы... Но не сейчас.",
    "emotion": "callback",
    "source": "extracted"
  },
  {
    "situation": "Состояние callback",
    "dialogue": "Позвоните в пятницу, ладно?",
    "emotion": "callback",
    "source": "extracted"
  },
  {
    "situation": "Состояние callback",
    "dialogue": "Обязательно решу. Потом.",
    "emotion": "callback",
    "source": "extracted"
  },
  {
    "situation": "Состояние hostile",
    "dialogue": "Ой, знаете... наверное, не надо.",
    "emotion": "hostile",
    "source": "extracted"
  },
  {
    "situation": "Состояние hostile",
    "dialogue": "Я тут подумал — обойдусь.",
    "emotion": "hostile",
    "source": "extracted"
  },
  {
    "situation": "Состояние hostile",
    "dialogue": "Не-не, спасибо. Я сам как-нибудь.",
    "emotion": "hostile",
    "source": "extracted"
  },
  {
    "situation": "Состояние hostile",
    "dialogue": "Давайте в другой раз. Может быть.",
    "emotion": "hostile",
    "source": "extracted"
  },
  {
    "situation": "Состояние hostile",
    "dialogue": "Простите, но нет. Наверное.",
    "emotion": "hostile",
    "source": "extracted"
  },
  {
    "situation": "Состояние hangup",
    "dialogue": "Ну ладно, спасибо. До свидания.",
    "emotion": "hangup",
    "source": "extracted"
  },
  {
    "situation": "Состояние hangup",
    "dialogue": "Да-да, перезвоните.",
    "emotion": "hangup",
    "source": "extracted"
  },
  {
    "situation": "Состояние hangup",
    "dialogue": "Хорошо. Пока.",
    "emotion": "hangup",
    "source": "extracted"
  },
  {
    "situation": "Состояние hangup",
    "dialogue": "Ага. Ладно.",
    "emotion": "hangup",
    "source": "extracted"
  },
  {
    "situation": "Состояние hangup",
    "dialogue": "Спасибо. Я подумаю.",
    "emotion": "hangup",
    "source": "extracted"
  }
]